zoom/__init__.py
zoom/__version__.py
zoom/zoom_client.py
zoom/zoom_error.py
zoom/zoom_file_dep.py
zoom/zoom_git_module.py
zoom/zoom_io.py
zoom/zoom_project.py
zoom/zoom_resource.py
zoom-0.0.15.dist-info/DESCRIPTION.rst
zoom-0.0.15.dist-info/METADATA
zoom-0.0.15.dist-info/RECORD
zoom-0.0.15.dist-info/WHEEL
zoom-0.0.15.dist-info/entry_points.txt
zoom-0.0.15.dist-info/metadata.json
zoom-0.0.15.dist-info/top_level.txt
