Metadata-Version: 2.0
Name: zoom
Version: 0.0.15
Summary: Distributed project management
Home-page: https://github.com/ssagar0/zoom
Author: Sunny Sagar
Author-email: trexinabluecape@gmail.com
License: MIT
Keywords: git repo
Platform: UNKNOWN
Classifier: License :: OSI Approved :: MIT License
Classifier: Programming Language :: Python :: 2.7
Classifier: Topic :: Software Development :: Version Control
Requires-Dist: click
Requires-Dist: pyaml
